{
  "name": "html-minifier-next",
  "version": "1.0.0",
  "description": "Super-configurable and well-tested web page minifier (enhanced successor of HTML Minifier). Handles HTML, CSS, JS, and SVG minification.",
  "commands": [
    {
      "name": "version",
      "description": "Show html-minifier-next version",
      "command": "html-minifier-next --version"
    },
    {
      "name": "minify",
      "description": "Minify HTML, CSS, JS, and SVG files",
      "command": "html-minifier-next",
      "args": true
    }
  ],
  "checks": [
    {
      "name": "html-minifier-next",
      "type": "binary",
      "command": "html-minifier-next --version"
    }
  ]
}
