{
  "name": "aq",
  "version": "0.1.0",
  "description": "Query AWS resources with SQL for easy data extraction and analysis",
  "source": "https://github.com/lebinh/aq",
  "checks": [
    {
      "type": "binary",
      "name": "aq"
    }
  ],
  "install_guidance": {
    "plugin": "aq",
    "binary": "aq",
    "check": "which aq",
    "install_steps": [
      "pip install aq",
      "Verify: aq --version",
      "supercli plugins install ./plugins/aq --on-conflict replace --json"
    ]
  },
  "learn": {
    "file": "skills/quickstart/SKILL.md"
  },
  "commands": [
    {
      "namespace": "aq",
      "resource": "self",
      "action": "version",
      "description": "Print aq version",
      "adapter": "process",
      "adapterConfig": {
        "command": "aq",
        "missingDependencyHelp": "Install aq: pip install aq",
        "baseArgs": [
          "--version"
        ]
      },
      "args": []
    },
    {
      "namespace": "aq",
      "resource": "resource",
      "action": "query",
      "description": "query resource via aq",
      "adapter": "process",
      "adapterConfig": {
        "command": "aq",
        "missingDependencyHelp": "Install aq: pip install aq",
        "baseArgs": [
          "query"
        ],
        "passthrough": true,
        "timeout_ms": 300000
      },
      "args": [
        {
          "name": "args",
          "type": "string",
          "required": false,
          "description": "Additional arguments"
        }
      ]
    },
    {
      "namespace": "aq",
      "resource": "resource",
      "action": "list",
      "description": "list resource via aq",
      "adapter": "process",
      "adapterConfig": {
        "command": "aq",
        "missingDependencyHelp": "Install aq: pip install aq",
        "baseArgs": [
          "list"
        ],
        "passthrough": true,
        "timeout_ms": 300000
      },
      "args": [
        {
          "name": "args",
          "type": "string",
          "required": false,
          "description": "Additional arguments"
        }
      ]
    },
    {
      "namespace": "aq",
      "resource": "service",
      "action": "set",
      "description": "set service via aq",
      "adapter": "process",
      "adapterConfig": {
        "command": "aq",
        "missingDependencyHelp": "Install aq: pip install aq",
        "baseArgs": [
          "--service"
        ],
        "passthrough": true,
        "timeout_ms": 300000
      },
      "args": [
        {
          "name": "args",
          "type": "string",
          "required": false,
          "description": "Additional arguments"
        }
      ]
    },
    {
      "namespace": "aq",
      "resource": "output",
      "action": "set",
      "description": "set output via aq",
      "adapter": "process",
      "adapterConfig": {
        "command": "aq",
        "missingDependencyHelp": "Install aq: pip install aq",
        "baseArgs": [
          "--output"
        ],
        "passthrough": true,
        "timeout_ms": 300000
      },
      "args": [
        {
          "name": "args",
          "type": "string",
          "required": false,
          "description": "Additional arguments"
        }
      ]
    },
    {
      "namespace": "aq",
      "resource": "format",
      "action": "set",
      "description": "set format via aq",
      "adapter": "process",
      "adapterConfig": {
        "command": "aq",
        "missingDependencyHelp": "Install aq: pip install aq",
        "baseArgs": [
          "--format"
        ],
        "passthrough": true,
        "timeout_ms": 300000
      },
      "args": [
        {
          "name": "args",
          "type": "string",
          "required": false,
          "description": "Additional arguments"
        }
      ]
    },
    {
      "namespace": "aq",
      "resource": "config",
      "action": "show",
      "description": "show config via aq",
      "adapter": "process",
      "adapterConfig": {
        "command": "aq",
        "missingDependencyHelp": "Install aq: pip install aq",
        "baseArgs": [
          "--config"
        ],
        "passthrough": true,
        "timeout_ms": 30000
      },
      "args": [
        {
          "name": "args",
          "type": "string",
          "required": false,
          "description": "Additional arguments"
        }
      ]
    },
    {
      "namespace": "aq",
      "resource": "verbose",
      "action": "set",
      "description": "set verbose via aq",
      "adapter": "process",
      "adapterConfig": {
        "command": "aq",
        "missingDependencyHelp": "Install aq: pip install aq",
        "baseArgs": [
          "--verbose"
        ],
        "passthrough": true,
        "timeout_ms": 30000
      },
      "args": [
        {
          "name": "args",
          "type": "string",
          "required": false,
          "description": "Additional arguments"
        }
      ]
    },
    {
      "namespace": "aq",
      "resource": "help",
      "action": "show",
      "description": "show help via aq",
      "adapter": "process",
      "adapterConfig": {
        "command": "aq",
        "missingDependencyHelp": "Install aq: pip install aq",
        "baseArgs": [
          "--help"
        ],
        "passthrough": true,
        "timeout_ms": 30000
      },
      "args": [
        {
          "name": "args",
          "type": "string",
          "required": false,
          "description": "Additional arguments"
        }
      ]
    },
    {
      "namespace": "aq",
      "resource": "_",
      "action": "_",
      "description": "_ _ via aq",
      "adapter": "process",
      "adapterConfig": {
        "command": "aq",
        "missingDependencyHelp": "Install aq: pip install aq",
        "passthrough": true
      },
      "args": [
        {
          "name": "args",
          "type": "string",
          "required": false,
          "description": "Additional arguments"
        }
      ]
    }
  ]
}