{
  "name": "caddy",
  "version": "0.1.0",
  "description": "Fast and extensible multi-platform HTTP/2 web server",
  "source": "https://github.com/caddyserver/caddy",
  "checks": [
    {
      "type": "binary",
      "name": "caddy"
    }
  ],
  "install_guidance": {
    "plugin": "caddy",
    "binary": "caddy",
    "check": "which caddy",
    "install_steps": [
      "brew install caddy",
      "Verify: caddy --version",
      "supercli plugins install ./plugins/caddy --on-conflict replace --json"
    ]
  },
  "learn": {
    "file": "skills/quickstart/SKILL.md"
  },
  "commands": [
    {
      "namespace": "caddy",
      "resource": "self",
      "action": "version",
      "description": "Print caddy version",
      "adapter": "process",
      "adapterConfig": {
        "command": "caddy",
        "missingDependencyHelp": "Install caddy: brew install caddy",
        "baseArgs": [
          "version"
        ]
      },
      "args": []
    },
    {
      "namespace": "caddy",
      "resource": "config",
      "action": "adapt",
      "description": "adapt config via caddy",
      "adapter": "process",
      "adapterConfig": {
        "command": "caddy",
        "missingDependencyHelp": "Install caddy: brew install caddy",
        "baseArgs": [
          "adapt"
        ],
        "passthrough": true,
        "timeout_ms": 30000
      },
      "args": [
        {
          "name": "args",
          "type": "string",
          "required": false,
          "description": "Additional arguments"
        }
      ]
    },
    {
      "namespace": "caddy",
      "resource": "server",
      "action": "run",
      "description": "run server via caddy",
      "adapter": "process",
      "adapterConfig": {
        "command": "caddy",
        "missingDependencyHelp": "Install caddy: brew install caddy",
        "baseArgs": [
          "run"
        ],
        "passthrough": true,
        "timeout_ms": 300000
      },
      "args": [
        {
          "name": "args",
          "type": "string",
          "required": false,
          "description": "Additional arguments"
        }
      ]
    },
    {
      "namespace": "caddy",
      "resource": "reverse-proxy",
      "action": "start",
      "description": "start reverse-proxy via caddy",
      "adapter": "process",
      "adapterConfig": {
        "command": "caddy",
        "missingDependencyHelp": "Install caddy: brew install caddy",
        "baseArgs": [
          "reverse-proxy"
        ],
        "passthrough": true,
        "timeout_ms": 300000
      },
      "args": [
        {
          "name": "args",
          "type": "string",
          "required": false,
          "description": "Additional arguments"
        }
      ]
    },
    {
      "namespace": "caddy",
      "resource": "_",
      "action": "_",
      "description": "_ _ via caddy",
      "adapter": "process",
      "adapterConfig": {
        "command": "caddy",
        "missingDependencyHelp": "Install caddy: brew install caddy",
        "passthrough": true
      },
      "args": [
        {
          "name": "args",
          "type": "string",
          "required": false,
          "description": "Additional arguments"
        }
      ]
    }
  ]
}